staticfg/__init__.py
staticfg/builder.py
staticfg/model.py
staticfg-0.9.2.dist-info/LICENSE
staticfg-0.9.2.dist-info/METADATA
staticfg-0.9.2.dist-info/WHEEL
staticfg-0.9.2.dist-info/top_level.txt
staticfg-0.9.2.dist-info/RECORD
